{
  "auth": {
    "usebetter6cc6b009": {
      "service": "Cognito",
      "providerPlugin": "awscloudformation",
      "dependsOn": [],
      "customAuth": false,
      "frontendAuthConfig": {
        "socialProviders": [],
        "usernameAttributes": [],
        "signupAttributes": [
          "EMAIL"
        ],
        "passwordProtectionSettings": {
          "passwordPolicyMinLength": 8,
          "passwordPolicyCharacters": []
        },
        "mfaConfiguration": "OFF",
        "mfaTypes": [
          "SMS"
        ],
        "verificationMechanisms": [
          "EMAIL"
        ]
      }
    }
  },
  "storage": {
    "usebettercontent": {
      "service": "S3",
      "providerPlugin": "awscloudformation",
      "dependsOn": []
    }
  },
  "api": {
    "usebetter": {
      "service": "AppSync",
      "providerPlugin": "awscloudformation",
      "dependsOn": [
        {
          "category": "auth",
          "resourceName": "usebetter6cc6b009",
          "attributes": [
            "UserPoolId"
          ]
        }
      ],
      "output": {
        "authConfig": {
          "defaultAuthentication": {
            "authenticationType": "AMAZON_COGNITO_USER_POOLS",
            "userPoolConfig": {
              "userPoolId": "authusebetter6cc6b009"
            }
          },
          "additionalAuthenticationProviders": []
        }
      }
    }
  }
}